Workbook
Name 继续教育类型: [1]下拉值!$C$1:$D$1
Name 省份: [1]下拉值!$F$1:$AJ$1

Sheet 1月
A1: 模板导入说明： 1.前三行数据，系统不读取，不需要删除 2.工资模板导入时只支持第一个sheet数据导入，导入某月份的工资表时，需要将该月份工资表的sheet移动到第一个sheet位置
A2: 工资表--1月
A3: 工号 | B3: 姓名 | C3: 部门 | D3: 身份证号码 | E3: 计薪日 | F3: 出勤天数 | G3: 基本工资 | H3: 出勤工资 | I3: 奖金 | J3: 津贴 | K3: 补贴 | L3: 其他应发1 | M3: 其他应发2 | N3: 应发合计 | O3: 养老保险 | P3: 医疗保险 | Q3: 失业保险 | R3: 公积金 | S3: 累计应发 | T3: 累计社保公积金 | U3: 累计子女教育 | V3: 累计住房贷款利息 | W3: 累计住房租金 | X3: 累计赡养父母 | Y3: 累计继续教育 | Z3: 累计婴幼儿照护费用 | AA3: 累计应缴个税 | AB3: 累计已缴个税 | AC3: 本月应缴个税 | AD3: 个人还款 | AE3: 其他扣款1 | AF3: 其他扣款2 | AG3: 实发工资
H4: =IFERROR(ROUND(F4/E4*G4,2),0) -> 0 | N4: =SUM(H4:M4) -> 0 | S4: =N4 -> 0 | T4: =SUM(O4:R4) -> 0 | AA4: =ROUND(MAX((S4-5000-T4-U4-V4-W4-X4-Y4-Z4)*{0.03;0.1;0.2;0.25;0.3;0.35;0.45}-{0;2520;16920;31920;52920;85920;181920},0),2) -> 0 | AB4: 0 | AC4: =AA4-AB4 -> 0 | AG4: =N4-O4-P4-Q4-R4-AC4-AD4-AE4-AF4 -> 0
H5: =IFERROR(ROUND(F5/E5*G5,2),0) -> 0 | N5: =SUM(H5:M5) -> 0 | S5: =N5 -> 0 | T5: =SUM(O5:R5) -> 0 | AA5: =ROUND(MAX((S5-5000-T5-U5-V5-W5-X5-Y5-Z5)*{0.03;0.1;0.2;0.25;0.3;0.35;0.45}-{0;2520;16920;31920;52920;85920;181920},0),2) -> 0 | AB5: 0 | AC5: =AA5-AB5 -> 0 | AG5: =N5-O5-P5-Q5-R5-AC5-AD5-AE5-AF5 -> 0
B16: 合计

Sheet 2月
A1: 模板导入说明： 1.前三行数据，系统不读取，不需要删除 2.工资模板导入时只支持第一个sheet数据导入，导入某月份的工资表时，需要将该月份工资表的sheet移动到第一个sheet位置
A2: 工资表--2月
A3: 工号 | B3: 姓名 | C3: 部门 | D3: 身份证号码 | E3: 计薪日 | F3: 出勤天数 | G3: 基本工资 | H3: 出勤工资 | I3: 奖金 | J3: 津贴 | K3: 补贴 | L3: 其他应发1 | M3: 其他应发2 | N3: 应发合计 | O3: 养老保险 | P3: 医疗保险 | Q3: 失业保险 | R3: 公积金 | S3: 累计应发 | T3: 累计社保公积金 | U3: 累计子女教育 | V3: 累计住房贷款利息 | W3: 累计住房租金 | X3: 累计赡养父母 | Y3: 累计继续教育 | Z3: 累计婴幼儿照护费用 | AA3: 累计应缴个税 | AB3: 累计已缴个税 | AC3: 本月应缴个税 | AD3: 个人还款 | AE3: 其他扣款1 | AF3: 其他扣款2 | AG3: 实发工资
H4: =IFERROR(ROUND(F4/E4*G4,2),0) -> 0 | N4: =SUM(H4:M4) -> 0 | S4: =N4+IFERROR(VLOOKUP(A4,'1月'!A:S,MATCH($S$3,'1月'!$A$3:$S$3,0),0),0) -> 0 | T4: =SUM(O4:R4)+IFERROR(VLOOKUP(A4,'1月'!A:T,MATCH($T$3,'1月'!$A$3:$T$3,0),0),0) -> 0 | AA4: =ROUND(MAX((S4-2*5000-T4-U4-V4-W4-X4-Y4-Z4)*{0.03;0.1;0.2;0.25;0.3;0.35;0.45}-{0;2520;16920;31920;52920;85920;181920},0),2) -> 0 | AB4: =IFERROR(VLOOKUP(A4,'1月'!A:AA,MATCH($AA$3,'1月'!$A$3:$AA$3,0),0),0) -> 0 | AC4: =AA4-AB4 -> 0 | AG4: =N4-O4-P4-Q4-R4-AC4-AD4-AE4-AF4 -> 0
H5: =IFERROR(ROUND(F5/E5*G5,2),0) -> 0 | N5: =SUM(H5:M5) -> 0 | S5: =N5+IFERROR(VLOOKUP(A5,'1月'!A:S,MATCH($S$3,'1月'!$A$3:$S$3,0),0),0) -> 0 | T5: =SUM(O5:R5)+IFERROR(VLOOKUP(A5,'1月'!A:T,MATCH($T$3,'1月'!$A$3:$T$3,0),0),0) -> 0 | AA5: =ROUND(MAX((S5-2*5000-T5-U5-V5-W5-X5-Z5)*{0.03;0.1;0.2;0.25;0.3;0.35;0.45}-{0;2520;16920;31920;52920;85920;181920},0),2) -> 0 | AB5: =IFERROR(VLOOKUP(A5,'1月'!A:AA,MATCH($AA$3,'1月'!$A$3:$AA$3,0),0),0) -> 0 | AC5: =AA5-AB5 -> 0 | AG5: =N5-O5-P5-Q5-R5-AC5-AD5-AE5-AF5 -> 0
B16: 合计

Sheet 3月
A1: 模板导入说明： 1.前三行数据，系统不读取，不需要删除 2.工资模板导入时只支持第一个sheet数据导入，导入某月份的工资表时，需要将该月份工资表的sheet移动到第一个sheet位置
A2: 工资表-3月
A3: 工号 | B3: 姓名 | C3: 部门 | D3: 身份证号码 | E3: 计薪日 | F3: 出勤天数 | G3: 基本工资 | H3: 出勤工资 | I3: 奖金 | J3: 津贴 | K3: 补贴 | L3: 其他应发1 | M3: 其他应发2 | N3: 应发合计 | O3: 养老保险 | P3: 医疗保险 | Q3: 失业保险 | R3: 公积金 | S3: 累计应发 | T3: 累计社保公积金 | U3: 累计子女教育 | V3: 累计住房贷款利息 | W3: 累计住房租金 | X3: 累计赡养父母 | Y3: 累计继续教育 | Z3: 累计婴幼儿照护费用 | AA3: 累计应缴个税 | AB3: 累计已缴个税 | AC3: 本月应缴个税 | AD3: 个人还款 | AE3: 其他扣款1 | AF3: 其他扣款2 | AG3: 实发工资
H4: =IFERROR(ROUND(F4/E4*G4,2),0) -> 0 | N4: =SUM(H4:M4) -> 0 | S4: =N4+IFERROR(VLOOKUP(A4,'2月'!A:S,MATCH($S$3,'2月'!$A$3:$S$3,0),0),0) -> 0 | T4: =SUM(O4:R4)+IFERROR(VLOOKUP(A4,'2月'!A:T,MATCH($T$3,'2月'!$A$3:$T$3,0),0),0) -> 0 | AA4: =ROUND(MAX((S4-3*5000-T4-U4-V4-W4-X4-Y4-Z4)*{0.03;0.1;0.2;0.25;0.3;0.35;0.45}-{0;2520;16920;31920;52920;85920;181920},0),2) -> 0 | AB4: =IFERROR(VLOOKUP(A4,'2月'!A:AA,MATCH($AA$3,'2月'!$A$3:$AA$3,0),0),0) -> 0 | AC4: =AA4-AB4 -> 0 | AG4: =N4-O4-P4-Q4-R4-AC4-AD4-AE4-AF4 -> 0
H5: =IFERROR(ROUND(F5/E5*G5,2),0) -> 0 | N5: =SUM(H5:M5) -> 0 | S5: =N5+IFERROR(VLOOKUP(A5,'2月'!A:S,MATCH($S$3,'2月'!$A$3:$S$3,0),0),0) -> 0 | T5: =SUM(O5:R5)+IFERROR(VLOOKUP(A5,'2月'!A:T,MATCH($T$3,'2月'!$A$3:$T$3,0),0),0) -> 0 | AA5: =ROUND(MAX((S5-3*5000-T5-U5-V5-W5-X5-Y5-Y5-Z5)*{0.03;0.1;0.2;0.25;0.3;0.35;0.45}-{0;2520;16920;31920;52920;85920;181920},0),2) -> 0 | AB5: =IFERROR(VLOOKUP(A5,'2月'!A:AA,MATCH($AA$3,'2月'!$A$3:$AA$3,0),0),0) -> 0 | AC5: =AA5-AB5 -> 0 | AG5: =N5-O5-P5-Q5-R5-AC5-AD5-AE5-AF5 -> 0
B16: 合计

Sheet 4月
A1: 模板导入说明： 1.前三行数据，系统不读取，不需要删除 2.工资模板导入时只支持第一个sheet数据导入，导入某月份的工资表时，需要将该月份工资表的sheet移动到第一个sheet位置
A2: 工资表-4月
A3: 工号 | B3: 姓名 | C3: 部门 | D3: 身份证号码 | E3: 计薪日 | F3: 出勤天数 | G3: 基本工资 | H3: 出勤工资 | I3: 奖金 | J3: 津贴 | K3: 补贴 | L3: 其他应发1 | M3: 其他应发2 | N3: 应发合计 | O3: 养老保险 | P3: 医疗保险 | Q3: 失业保险 | R3: 公积金 | S3: 累计应发 | T3: 累计社保公积金 | U3: 累计子女教育 | V3: 累计住房贷款利息 | W3: 累计住房租金 | X3: 累计赡养父母 | Y3: 累计继续教育 | Z3: 累计婴幼儿照护费用 | AA3: 累计应缴个税 | AB3: 累计已缴个税 | AC3: 本月应缴个税 | AD3: 个人还款 | AE3: 其他扣款1 | AF3: 其他扣款2 | AG3: 实发工资
H4: =IFERROR(ROUND(F4/E4*G4,2),0) -> 0 | N4: =SUM(H4:M4) -> 0 | S4: =N4+IFERROR(VLOOKUP(A4,'3月'!A:S,MATCH($S$3,'3月'!$A$3:$S$3,0),0),0) -> 0 | T4: =SUM(O4:R4)+IFERROR(VLOOKUP(A4,'3月'!A:T,MATCH($T$3,'3月'!$A$3:$T$3,0),0),0) -> 0 | AA4: =ROUND(MAX((S4-4*5000-T4-U4-V4-W4-X4-Y4-Z4)*{0.03;0.1;0.2;0.25;0.3;0.35;0.45}-{0;2520;16920;31920;52920;85920;181920},0),2) -> 0 | AB4: =IFERROR(VLOOKUP(A4,'3月'!A:AA,MATCH($AA$3,'3月'!$A$3:$AA$3,0),0),0) -> 0 | AC4: =AA4-AB4 -> 0 | AG4: =N4-O4-P4-Q4-R4-AC4-AD4-AE4-AF4 -> 0
H5: =IFERROR(ROUND(F5/E5*G5,2),0) -> 0 | N5: =SUM(H5:M5) -> 0 | S5: =N5+IFERROR(VLOOKUP(A5,'3月'!A:S,MATCH($S$3,'3月'!$A$3:$S$3,0),0),0) -> 0 | T5: =SUM(O5:R5)+IFERROR(VLOOKUP(A5,'3月'!A:T,MATCH($T$3,'3月'!$A$3:$T$3,0),0),0) -> 0 | AA5: =ROUND(MAX((S5-4*5000-T5-U5-V5-W5-X5-Y5-Z5)*{0.03;0.1;0.2;0.25;0.3;0.35;0.45}-{0;2520;16920;31920;52920;85920;181920},0),2) -> 0 | AB5: =IFERROR(VLOOKUP(A5,'3月'!A:AA,MATCH($AA$3,'3月'!$A$3:$AA$3,0),0),0) -> 0 | AC5: =AA5-AB5 -> 0 | AG5: =N5-O5-P5-Q5-R5-AC5-AD5-AE5-AF5 -> 0
B16: 合计

Sheet 5月
A1: 模板导入说明： 1.前三行数据，系统不读取，不需要删除 2.工资模板导入时只支持第一个sheet数据导入，导入某月份的工资表时，需要将该月份工资表的sheet移动到第一个sheet位置
A2: 工资表-5月
A3: 工号 | B3: 姓名 | C3: 部门 | D3: 身份证号码 | E3: 计薪日 | F3: 出勤天数 | G3: 基本工资 | H3: 出勤工资 | I3: 奖金 | J3: 津贴 | K3: 补贴 | L3: 其他应发1 | M3: 其他应发2 | N3: 应发合计 | O3: 养老保险 | P3: 医疗保险 | Q3: 失业保险 | R3: 公积金 | S3: 累计应发 | T3: 累计社保公积金 | U3: 累计子女教育 | V3: 累计住房贷款利息 | W3: 累计住房租金 | X3: 累计赡养父母 | Y3: 累计继续教育 | Z3: 累计婴幼儿照护费用 | AA3: 累计应缴个税 | AB3: 累计已缴个税 | AC3: 本月应缴个税 | AD3: 个人还款 | AE3: 其他扣款1 | AF3: 其他扣款2 | AG3: 实发工资
H4: =IFERROR(ROUND(F4/E4*G4,2),0) -> 0 | N4: =SUM(H4:M4) -> 0 | S4: =N4+IFERROR(VLOOKUP(A4,'4月'!A:S,MATCH($S$3,'4月'!$A$3:$S$3,0),0),0) -> 0 | T4: =SUM(O4:R4)+IFERROR(VLOOKUP(A4,'4月'!A:T,MATCH($T$3,'4月'!$A$3:$T$3,0),0),0) -> 0 | AA4: =ROUND(MAX((S4-5*5000-T4-U4-V4-W4-X4-Y4-Z4)*{0.03;0.1;0.2;0.25;0.3;0.35;0.45}-{0;2520;16920;31920;52920;85920;181920},0),2) -> 0 | AB4: =IFERROR(VLOOKUP(A4,'4月'!A:AA,MATCH($AA$3,'4月'!$A$3:$AA$3,0),0),0) -> 0 | AC4: =AA4-AB4 -> 0 | AG4: =N4-O4-P4-Q4-R4-AC4-AD4-AE4-AF4 -> 0
H5: =IFERROR(ROUND(F5/E5*G5,2),0) -> 0 | N5: =SUM(H5:M5) -> 0 | S5: =N5+IFERROR(VLOOKUP(A5,'4月'!A:S,MATCH($S$3,'4月'!$A$3:$S$3,0),0),0) -> 0 | T5: =SUM(O5:R5)+IFERROR(VLOOKUP(A5,'4月'!A:T,MATCH($T$3,'4月'!$A$3:$T$3,0),0),0) -> 0 | AA5: =ROUND(MAX((S5-5*5000-T5-U5-V5-W5-X5-Y5-Z5)*{0.03;0.1;0.2;0.25;0.3;0.35;0.45}-{0;2520;16920;31920;52920;85920;181920},0),2) -> 0 | AB5: =IFERROR(VLOOKUP(A5,'4月'!A:AA,MATCH($AA$3,'4月'!$A$3:$AA$3,0),0),0) -> 0 | AC5: =AA5-AB5 -> 0 | AG5: =N5-O5-P5-Q5-R5-AC5-AD5-AE5-AF5 -> 0
B16: 合计

Sheet 6月
A1: 模板导入说明： 1.前三行数据，系统不读取，不需要删除 2.工资模板导入时只支持第一个sheet数据导入，导入某月份的工资表时，需要将该月份工资表的sheet移动到第一个sheet位置
A2: 工资表-6月
A3: 工号 | B3: 姓名 | C3: 部门 | D3: 身份证号码 | E3: 计薪日 | F3: 出勤天数 | G3: 基本工资 | H3: 出勤工资 | I3: 奖金 | J3: 津贴 | K3: 补贴 | L3: 其他应发1 | M3: 其他应发2 | N3: 应发合计 | O3: 养老保险 | P3: 医疗保险 | Q3: 失业保险 | R3: 公积金 | S3: 累计应发 | T3: 累计社保公积金 | U3: 累计子女教育 | V3: 累计住房贷款利息 | W3: 累计住房租金 | X3: 累计赡养父母 | Y3: 累计继续教育 | Z3: 累计婴幼儿照护费用 | AA3: 累计应缴个税 | AB3: 累计已缴个税 | AC3: 本月应缴个税 | AD3: 个人还款 | AE3: 其他扣款1 | AF3: 其他扣款2 | AG3: 实发工资
H4: =IFERROR(ROUND(F4/E4*G4,2),0) -> 0 | N4: =SUM(H4:M4) -> 0 | S4: =N4+IFERROR(VLOOKUP(A4,'5月'!A:S,MATCH($S$3,'5月'!$A$3:$S$3,0),0),0) -> 0 | T4: =SUM(O4:R4)+IFERROR(VLOOKUP(A4,'5月'!A:T,MATCH($T$3,'5月'!$A$3:$T$3,0),0),0) -> 0 | AA4: =ROUND(MAX((S4-6*5000-T4-U4-V4-W4-X4-Y4-Z4)*{0.03;0.1;0.2;0.25;0.3;0.35;0.45}-{0;2520;16920;31920;52920;85920;181920},0),2) -> 0 | AB4: =IFERROR(VLOOKUP(A4,'5月'!A:AA,MATCH($AA$3,'5月'!$A$3:$AA$3,0),0),0) -> 0 | AC4: =AA4-AB4 -> 0 | AG4: =N4-O4-P4-Q4-R4-AC4-AD4-AE4-AF4 -> 0
H5: =IFERROR(ROUND(F5/E5*G5,2),0) -> 0 | N5: =SUM(H5:M5) -> 0 | S5: =N5+IFERROR(VLOOKUP(A5,'5月'!A:S,MATCH($S$3,'5月'!$A$3:$S$3,0),0),0) -> 0 | T5: =SUM(O5:R5)+IFERROR(VLOOKUP(A5,'5月'!A:T,MATCH($T$3,'5月'!$A$3:$T$3,0),0),0) -> 0 | AA5: =ROUND(MAX((S5-6*5000-T5-U5-V5-W5-X5-Y5-Z5)*{0.03;0.1;0.2;0.25;0.3;0.35;0.45}-{0;2520;16920;31920;52920;85920;181920},0),2) -> 0 | AB5: =IFERROR(VLOOKUP(A5,'5月'!A:AA,MATCH($AA$3,'5月'!$A$3:$AA$3,0),0),0) -> 0 | AC5: =AA5-AB5 -> 0 | AG5: =N5-O5-P5-Q5-R5-AC5-AD5-AE5-AF5 -> 0
B16: 合计

Sheet 7月
A1: 模板导入说明： 1.前三行数据，系统不读取，不需要删除 2.工资模板导入时只支持第一个sheet数据导入，导入某月份的工资表时，需要将该月份工资表的sheet移动到第一个sheet位置
A2: 工资表-7月
A3: 工号 | B3: 姓名 | C3: 部门 | D3: 身份证号码 | E3: 计薪日 | F3: 出勤天数 | G3: 基本工资 | H3: 出勤工资 | I3: 奖金 | J3: 津贴 | K3: 补贴 | L3: 其他应发1 | M3: 其他应发2 | N3: 应发合计 | O3: 养老保险 | P3: 医疗保险 | Q3: 失业保险 | R3: 公积金 | S3: 累计应发 | T3: 累计社保公积金 | U3: 累计子女教育 | V3: 累计住房贷款利息 | W3: 累计住房租金 | X3: 累计赡养父母 | Y3: 累计继续教育 | Z3: 累计婴幼儿照护费用 | AA3: 累计应缴个税 | AB3: 累计已缴个税 | AC3: 本月应缴个税 | AD3: 个人还款 | AE3: 其他扣款1 | AF3: 其他扣款2 | AG3: 实发工资
H4: =IFERROR(ROUND(F4/E4*G4,2),0) -> 0 | N4: =SUM(H4:M4) -> 0 | S4: =N4+IFERROR(VLOOKUP(A4,'6月'!A:S,MATCH($S$3,'6月'!$A$3:$S$3,0),0),0) -> 0 | T4: =SUM(O4:R4)+IFERROR(VLOOKUP(A4,'6月'!A:T,MATCH($T$3,'6月'!$A$3:$T$3,0),0),0) -> 0 | AA4: =ROUND(MAX((S4-7*5000-T4-U4-V4-W4-X4-Y4-Z4)*{0.03;0.1;0.2;0.25;0.3;0.35;0.45}-{0;2520;16920;31920;52920;85920;181920},0),2) -> 0 | AB4: =IFERROR(VLOOKUP(A4,'6月'!A:AA,MATCH($AA$3,'6月'!$A$3:$AA$3,0),0),0) -> 0 | AC4: =AA4-AB4 -> 0 | AG4: =N4-O4-P4-Q4-R4-AC4-AD4-AE4-AF4 -> 0
H5: =IFERROR(ROUND(F5/E5*G5,2),0) -> 0 | N5: =SUM(H5:M5) -> 0 | S5: =N5+IFERROR(VLOOKUP(A5,'6月'!A:S,MATCH($S$3,'6月'!$A$3:$S$3,0),0),0) -> 0 | T5: =SUM(O5:R5)+IFERROR(VLOOKUP(A5,'6月'!A:T,MATCH($T$3,'6月'!$A$3:$T$3,0),0),0) -> 0 | AA5: =ROUND(MAX((S5-7*5000-T5-U5-V5-W5-X5-Y5-Z5)*{0.03;0.1;0.2;0.25;0.3;0.35;0.45}-{0;2520;16920;31920;52920;85920;181920},0),2) -> 0 | AB5: =IFERROR(VLOOKUP(A5,'6月'!A:AA,MATCH($AA$3,'6月'!$A$3:$AA$3,0),0),0) -> 0 | AC5: =AA5-AB5 -> 0 | AG5: =N5-O5-P5-Q5-R5-AC5-AD5-AE5-AF5 -> 0
B16: 合计

Sheet 8月
A1: 模板导入说明： 1.前三行数据，系统不读取，不需要删除 2.工资模板导入时只支持第一个sheet数据导入，导入某月份的工资表时，需要将该月份工资表的sheet移动到第一个sheet位置
A2: 工资表-8月
A3: 工号 | B3: 姓名 | C3: 部门 | D3: 身份证号码 | E3: 计薪日 | F3: 出勤天数 | G3: 基本工资 | H3: 出勤工资 | I3: 奖金 | J3: 津贴 | K3: 补贴 | L3: 其他应发1 | M3: 其他应发2 | N3: 应发合计 | O3: 养老保险 | P3: 医疗保险 | Q3: 失业保险 | R3: 公积金 | S3: 累计应发 | T3: 累计社保公积金 | U3: 累计子女教育 | V3: 累计住房贷款利息 | W3: 累计住房租金 | X3: 累计赡养父母 | Y3: 累计继续教育 | Z3: 累计婴幼儿照护费用 | AA3: 累计应缴个税 | AB3: 累计已缴个税 | AC3: 本月应缴个税 | AD3: 个人还款 | AE3: 其他扣款1 | AF3: 其他扣款2 | AG3: 实发工资
H4: =IFERROR(ROUND(F4/E4*G4,2),0) -> 0 | N4: =SUM(H4:M4) -> 0 | S4: =N4+IFERROR(VLOOKUP(A4,'7月'!A:S,MATCH($S$3,'7月'!$A$3:$S$3,0),0),0) -> 0 | T4: =SUM(O4:R4)+IFERROR(VLOOKUP(A4,'7月'!A:T,MATCH($T$3,'7月'!$A$3:$T$3,0),0),0) -> 0 | AA4: =ROUND(MAX((S4-8*5000-T4-U4-V4-W4-X4-Y4-Z4)*{0.03;0.1;0.2;0.25;0.3;0.35;0.45}-{0;2520;16920;31920;52920;85920;181920},0),2) -> 0 | AB4: =IFERROR(VLOOKUP(A4,'7月'!A:AA,MATCH($AA$3,'7月'!$A$3:$AA$3,0),0),0) -> 0 | AC4: =AA4-AB4 -> 0 | AG4: =N4-O4-P4-Q4-R4-AC4-AD4-AE4-AF4 -> 0
H5: =IFERROR(ROUND(F5/E5*G5,2),0) -> 0 | N5: =SUM(H5:M5) -> 0 | S5: =N5+IFERROR(VLOOKUP(A5,'7月'!A:S,MATCH($S$3,'7月'!$A$3:$S$3,0),0),0) -> 0 | T5: =SUM(O5:R5)+IFERROR(VLOOKUP(A5,'7月'!A:T,MATCH($T$3,'7月'!$A$3:$T$3,0),0),0) -> 0 | AA5: =ROUND(MAX((S5-8*5000-T5-U5-V5-W5-X5-Y5-Z5)*{0.03;0.1;0.2;0.25;0.3;0.35;0.45}-{0;2520;16920;31920;52920;85920;181920},0),2) -> 0 | AB5: =IFERROR(VLOOKUP(A5,'7月'!A:AA,MATCH($AA$3,'7月'!$A$3:$AA$3,0),0),0) -> 0 | AC5: =AA5-AB5 -> 0 | AG5: =N5-O5-P5-Q5-R5-AC5-AD5-AE5-AF5 -> 0
B16: 合计

Sheet 9月
A1: 模板导入说明： 1.前三行数据，系统不读取，不需要删除 2.工资模板导入时只支持第一个sheet数据导入，导入某月份的工资表时，需要将该月份工资表的sheet移动到第一个sheet位置
A2: 工资表-9月
A3: 工号 | B3: 姓名 | C3: 部门 | D3: 身份证号码 | E3: 计薪日 | F3: 出勤天数 | G3: 基本工资 | H3: 出勤工资 | I3: 奖金 | J3: 津贴 | K3: 补贴 | L3: 其他应发1 | M3: 其他应发2 | N3: 应发合计 | O3: 养老保险 | P3: 医疗保险 | Q3: 失业保险 | R3: 公积金 | S3: 累计应发 | T3: 累计社保公积金 | U3: 累计子女教育 | V3: 累计住房贷款利息 | W3: 累计住房租金 | X3: 累计赡养父母 | Y3: 累计继续教育 | Z3: 累计婴幼儿照护费用 | AA3: 累计应缴个税 | AB3: 累计已缴个税 | AC3: 本月应缴个税 | AD3: 个人还款 | AE3: 其他扣款1 | AF3: 其他扣款2 | AG3: 实发工资
H4: =IFERROR(ROUND(F4/E4*G4,2),0) -> 0 | N4: =SUM(H4:M4) -> 0 | S4: =N4+IFERROR(VLOOKUP(A4,'8月'!A:S,MATCH($S$3,'8月'!$A$3:$S$3,0),0),0) -> 0 | T4: =SUM(O4:R4)+IFERROR(VLOOKUP(A4,'8月'!A:T,MATCH($T$3,'8月'!$A$3:$T$3,0),0),0) -> 0 | AA4: =ROUND(MAX((S4-9*5000-T4-U4-V4-W4-X4-Y4-Z4)*{0.03;0.1;0.2;0.25;0.3;0.35;0.45}-{0;2520;16920;31920;52920;85920;181920},0),2) -> 0 | AB4: =IFERROR(VLOOKUP(A4,'8月'!A:AA,MATCH($AA$3,'8月'!$A$3:$AA$3,0),0),0) -> 0 | AC4: =AA4-AB4 -> 0 | AG4: =N4-O4-P4-Q4-R4-AC4-AD4-AE4-AF4 -> 0
H5: =IFERROR(ROUND(F5/E5*G5,2),0) -> 0 | N5: =SUM(H5:M5) -> 0 | S5: =N5+IFERROR(VLOOKUP(A5,'8月'!A:S,MATCH($S$3,'8月'!$A$3:$S$3,0),0),0) -> 0 | T5: =SUM(O5:R5)+IFERROR(VLOOKUP(A5,'8月'!A:T,MATCH($T$3,'8月'!$A$3:$T$3,0),0),0) -> 0 | AA5: =ROUND(MAX((S5-9*5000-T5-U5-V5-W5-X5-Y5-Z5)*{0.03;0.1;0.2;0.25;0.3;0.35;0.45}-{0;2520;16920;31920;52920;85920;181920},0),2) -> 0 | AB5: =IFERROR(VLOOKUP(A5,'8月'!A:AA,MATCH($AA$3,'8月'!$A$3:$AA$3,0),0),0) -> 0 | AC5: =AA5-AB5 -> 0 | AG5: =N5-O5-P5-Q5-R5-AC5-AD5-AE5-AF5 -> 0
B16: 合计

Sheet 10月
A1: 模板导入说明： 1.前三行数据，系统不读取，不需要删除 2.工资模板导入时只支持第一个sheet数据导入，导入某月份的工资表时，需要将该月份工资表的sheet移动到第一个sheet位置
A2: 工资表-10月
A3: 工号 | B3: 姓名 | C3: 部门 | D3: 身份证号码 | E3: 计薪日 | F3: 出勤天数 | G3: 基本工资 | H3: 出勤工资 | I3: 奖金 | J3: 津贴 | K3: 补贴 | L3: 其他应发1 | M3: 其他应发2 | N3: 应发合计 | O3: 养老保险 | P3: 医疗保险 | Q3: 失业保险 | R3: 公积金 | S3: 累计应发 | T3: 累计社保公积金 | U3: 累计子女教育 | V3: 累计住房贷款利息 | W3: 累计住房租金 | X3: 累计赡养父母 | Y3: 累计继续教育 | Z3: 累计婴幼儿照护费用 | AA3: 累计应缴个税 | AB3: 累计已缴个税 | AC3: 本月应缴个税 | AD3: 个人还款 | AE3: 其他扣款1 | AF3: 其他扣款2 | AG3: 实发工资
H4: =IFERROR(ROUND(F4/E4*G4,2),0) -> 0 | N4: =SUM(H4:M4) -> 0 | S4: =N4+IFERROR(VLOOKUP(A4,'9月'!A:S,MATCH($S$3,'9月'!$A$3:$S$3,0),0),0) -> 0 | T4: =SUM(O4:R4)+IFERROR(VLOOKUP(A4,'9月'!A:T,MATCH($T$3,'9月'!$A$3:$T$3,0),0),0) -> 0 | AA4: =ROUND(MAX((S4-10*5000-T4-U4-V4-W4-X4-Y4-Z4)*{0.03;0.1;0.2;0.25;0.3;0.35;0.45}-{0;2520;16920;31920;52920;85920;181920},0),2) -> 0 | AB4: =IFERROR(VLOOKUP(A4,'9月'!A:AA,MATCH($AA$3,'9月'!$A$3:$AA$3,0),0),0) -> 0 | AC4: =AA4-AB4 -> 0 | AG4: =N4-O4-P4-Q4-R4-AC4-AD4-AE4-AF4 -> 0
H5: =IFERROR(ROUND(F5/E5*G5,2),0) -> 0 | N5: =SUM(H5:M5) -> 0 | S5: =N5+IFERROR(VLOOKUP(A5,'9月'!A:S,MATCH($S$3,'9月'!$A$3:$S$3,0),0),0) -> 0 | T5: =SUM(O5:R5)+IFERROR(VLOOKUP(A5,'9月'!A:T,MATCH($T$3,'9月'!$A$3:$T$3,0),0),0) -> 0 | AA5: =ROUND(MAX((S5-10*5000-T5-U5-V5-W5-X5-Y5-Z5)*{0.03;0.1;0.2;0.25;0.3;0.35;0.45}-{0;2520;16920;31920;52920;85920;181920},0),2) -> 0 | AB5: =IFERROR(VLOOKUP(A5,'9月'!A:AA,MATCH($AA$3,'9月'!$A$3:$AA$3,0),0),0) -> 0 | AC5: =AA5-AB5 -> 0 | AG5: =N5-O5-P5-Q5-R5-AC5-AD5-AE5-AF5 -> 0
B16: 合计

Sheet 11月
A1: 模板导入说明： 1.前三行数据，系统不读取，不需要删除 2.工资模板导入时只支持第一个sheet数据导入，导入某月份的工资表时，需要将该月份工资表的sheet移动到第一个sheet位置
A2: 工资表-11月
A3: 工号 | B3: 姓名 | C3: 部门 | D3: 身份证号码 | E3: 计薪日 | F3: 出勤天数 | G3: 基本工资 | H3: 出勤工资 | I3: 奖金 | J3: 津贴 | K3: 补贴 | L3: 其他应发1 | M3: 其他应发2 | N3: 应发合计 | O3: 养老保险 | P3: 医疗保险 | Q3: 失业保险 | R3: 公积金 | S3: 累计应发 | T3: 累计社保公积金 | U3: 累计子女教育 | V3: 累计住房贷款利息 | W3: 累计住房租金 | X3: 累计赡养父母 | Y3: 累计继续教育 | Z3: 累计婴幼儿照护费用 | AA3: 累计应缴个税 | AB3: 累计已缴个税 | AC3: 本月应缴个税 | AD3: 个人还款 | AE3: 其他扣款1 | AF3: 其他扣款2 | AG3: 实发工资
H4: =IFERROR(ROUND(F4/E4*G4,2),0) -> 0 | N4: =SUM(H4:M4) -> 0 | S4: =N4+IFERROR(VLOOKUP(A4,'10月'!A:S,MATCH($S$3,'10月'!$A$3:$S$3,0),0),0) -> 0 | T4: =SUM(O4:R4)+IFERROR(VLOOKUP(A4,'10月'!A:T,MATCH($T$3,'10月'!$A$3:$T$3,0),0),0) -> 0 | AA4: =ROUND(MAX((S4-11*5000-T4-U4-V4-W4-X4-Y4-Z4)*{0.03;0.1;0.2;0.25;0.3;0.35;0.45}-{0;2520;16920;31920;52920;85920;181920},0),2) -> 0 | AB4: =IFERROR(VLOOKUP(A4,'10月'!A:AA,MATCH($AA$3,'10月'!$A$3:$AA$3,0),0),0) -> 0 | AC4: =AA4-AB4 -> 0 | AG4: =N4-O4-P4-Q4-R4-AC4-AD4-AE4-AF4 -> 0
H5: =IFERROR(ROUND(F5/E5*G5,2),0) -> 0 | N5: =SUM(H5:M5) -> 0 | S5: =N5+IFERROR(VLOOKUP(A5,'10月'!A:S,MATCH($S$3,'10月'!$A$3:$S$3,0),0),0) -> 0 | T5: =SUM(O5:R5)+IFERROR(VLOOKUP(A5,'10月'!A:T,MATCH($T$3,'10月'!$A$3:$T$3,0),0),0) -> 0 | AA5: =ROUND(MAX((S5-11*5000-T5-U5-V5-W5-X5-Y5-Z5)*{0.03;0.1;0.2;0.25;0.3;0.35;0.45}-{0;2520;16920;31920;52920;85920;181920},0),2) -> 0 | AB5: =IFERROR(VLOOKUP(A5,'10月'!A:AA,MATCH($AA$3,'10月'!$A$3:$AA$3,0),0),0) -> 0 | AC5: =AA5-AB5 -> 0 | AG5: =N5-O5-P5-Q5-R5-AC5-AD5-AE5-AF5 -> 0
B16: 合计

Sheet 12月
A1: 模板导入说明： 1.前三行数据，系统不读取，不需要删除 2.工资模板导入时只支持第一个sheet数据导入，导入某月份的工资表时，需要将该月份工资表的sheet移动到第一个sheet位置
A2: 工资表-12月
A3: 工号 | B3: 姓名 | C3: 部门 | D3: 身份证号码 | E3: 计薪日 | F3: 出勤天数 | G3: 基本工资 | H3: 出勤工资 | I3: 奖金 | J3: 津贴 | K3: 补贴 | L3: 其他应发1 | M3: 其他应发2 | N3: 应发工资 | O3: 养老保险 | P3: 医疗保险 | Q3: 失业保险 | R3: 公积金 | S3: 累计应发 | T3: 累计社保公积金 | U3: 累计子女教育 | V3: 累计住房贷款利息 | W3: 累计住房租金 | X3: 累计赡养父母 | Y3: 累计继续教育 | Z3: 累计婴幼儿照护费用 | AA3: 累计应缴个税 | AB3: 累计已缴个税 | AC3: 本月应缴个税 | AD3: 个人还款 | AE3: 其他扣款1 | AF3: 其他扣款2 | AG3: 实发工资
H4: =IFERROR(ROUND(F4/E4*G4,2),0) -> 0 | N4: =SUM(H4:M4) -> 0 | S4: =N4+IFERROR(VLOOKUP(A4,'11月'!A:S,MATCH($S$3,'11月'!$A$3:$S$3,0),0),0) -> 0 | T4: =SUM(O4:R4)+IFERROR(VLOOKUP(A4,'11月'!A:T,MATCH($T$3,'11月'!$A$3:$T$3,0),0),0) -> 0 | AA4: =ROUND(MAX((S4-12*5000-T4-U4-V4-W4-X4-Y4-Z4)*{0.03;0.1;0.2;0.25;0.3;0.35;0.45}-{0;2520;16920;31920;52920;85920;181920},0),2) -> 0 | AB4: =IFERROR(VLOOKUP(A4,'11月'!A:AA,MATCH($AA$3,'11月'!$A$3:$AA$3,0),0),0) -> 0 | AC4: =AA4-AB4 -> 0 | AG4: =N4-O4-P4-Q4-R4-AC4-AD4-AE4-AF4 -> 0
H5: =IFERROR(ROUND(F5/E5*G5,2),0) -> 0 | N5: =SUM(H5:M5) -> 0 | S5: =N5+IFERROR(VLOOKUP(A5,'11月'!A:S,MATCH($S$3,'11月'!$A$3:$S$3,0),0),0) -> 0 | T5: =SUM(O5:R5)+IFERROR(VLOOKUP(A5,'11月'!A:T,MATCH($T$3,'11月'!$A$3:$T$3,0),0),0) -> 0 | AA5: =ROUND(MAX((S5-12*5000-T5-U5-V5-W5-X5-Y5-Z5)*{0.03;0.1;0.2;0.25;0.3;0.35;0.45}-{0;2520;16920;31920;52920;85920;181920},0),2) -> 0 | AB5: =IFERROR(VLOOKUP(A5,'11月'!A:AA,MATCH($AA$3,'11月'!$A$3:$AA$3,0),0),0) -> 0 | AC5: =AA5-AB5 -> 0 | AG5: =N5-O5-P5-Q5-R5-AC5-AD5-AE5-AF5 -> 0
B16: 合计
